dreamlinktools/config.py
dreamlinktools/utils/vec3.py
dreamlinktools/zone_chunks.py
dreamlinktools-0.1.2.dist-info/METADATA
dreamlinktools-0.1.2.dist-info/WHEEL
dreamlinktools-0.1.2.dist-info/RECORD
