Metadata-Version: 2.1
Name: dreamlinktools
Version: 0.1.2
Summary: A collection of tools for working with Dreamlink zones.
Author: tlonny
Requires-Python: >=3.11,<4.0
Classifier: Programming Language :: Python :: 3
Classifier: Programming Language :: Python :: 3.11
Classifier: Programming Language :: Python :: 3.12
